tilda_wrapper_api/__init__.py
tilda_wrapper_api/client.py
tilda_wrapper_api/dataclasses/__init__.py
tilda_wrapper_api/dataclasses/base.py
tilda_wrapper_api/dataclasses/exceptions.py
tilda_wrapper_api/dataclasses/page.py
tilda_wrapper_api/dataclasses/project.py
tilda_wrapper_api-0.1.5.dist-info/LICENSE.md
tilda_wrapper_api-0.1.5.dist-info/METADATA
tilda_wrapper_api-0.1.5.dist-info/WHEEL
tilda_wrapper_api-0.1.5.dist-info/entry_points.txt
tilda_wrapper_api-0.1.5.dist-info/top_level.txt
tilda_wrapper_api-0.1.5.dist-info/RECORD
