Metadata-Version: 2.1
Name: tilda-wrapper-api
Version: 0.1.5
Summary: A python implementation of the Tilda API
Home-page: https://github.com/ozeranskiy/tilda_wrapper_api
Author: Sergey Ozeranskiy
Author-email: sergey.ozeranskiy@gmail.com
License: MIT
Keywords: tilda api
Platform: UNKNOWN
Classifier: Development Status :: 4 - Beta
Classifier: Intended Audience :: Developers
Classifier: License :: OSI Approved :: MIT License
Classifier: Natural Language :: English
Classifier: Operating System :: Unix
Classifier: Operating System :: OS Independent
Classifier: Programming Language :: Python :: 3.7
Requires-Dist: requests
Requires-Dist: dataclasses-json
